dshell/__init__.py
dshell/cog.py
dshell/jskshell.py
discordshell-0.0.2.dist-info/LICENSE
discordshell-0.0.2.dist-info/METADATA
discordshell-0.0.2.dist-info/WHEEL
discordshell-0.0.2.dist-info/top_level.txt
discordshell-0.0.2.dist-info/RECORD
