Metadata-Version: 2.1
Name: discordshell
Version: 0.0.2
Summary: DShell is a package that combines with discord.py and Jishaku to turn a Discord channel into a shell on which bash commands can be run.
Home-page: https://github.com/ImNimboss/dshell
Author: ImNimboss
Author-email: nimbossthegreat@gmail.com
License: MIT
Project-URL: Documentation, https://github.com/ImNimboss/dshell/tree/main/Documentation
Project-URL: Issue Tracker, https://github.com/ImNimboss/dshell/issues
Project-URL: Source, https://github.com/ImNimboss/dshell
Keywords: shell,discord,terminal,powershell,command-prompt,internet,console,shell-access,utility
Platform: UNKNOWN
Classifier: Development Status :: 5 - Production/Stable
Classifier: Intended Audience :: Developers
Classifier: License :: OSI Approved :: MIT License
Classifier: Natural Language :: English
Classifier: Operating System :: OS Independent
Classifier: Programming Language :: Python :: 3
Classifier: Programming Language :: Python :: 3.6
Classifier: Programming Language :: Python :: 3.7
Classifier: Programming Language :: Python :: 3.8
Classifier: Programming Language :: Python :: 3.9
Classifier: Programming Language :: Python :: 3.10
Classifier: Programming Language :: Python :: Implementation :: CPython
Classifier: Topic :: Communications
Classifier: Topic :: Communications :: Chat
Classifier: Topic :: Internet
Classifier: Topic :: Software Development :: Libraries
Classifier: Topic :: System :: Shells
Classifier: Topic :: System :: System Shells
Classifier: Topic :: System :: Systems Administration
Classifier: Topic :: Terminals
Classifier: Topic :: Terminals :: Terminal Emulators/X Terminals
Classifier: Topic :: Utilities
Requires-Python: >=3.6.0
